README.txt
setup.cfg
setup.py
docs/HISTORY.txt
docs/INSTALL.txt
docs/LICENSE.GPL
docs/LICENSE.txt
easyshop/__init__.py
easyshop.information.egg-info/PKG-INFO
easyshop.information.egg-info/SOURCES.txt
easyshop.information.egg-info/dependency_links.txt
easyshop.information.egg-info/entry_points.txt
easyshop.information.egg-info/namespace_packages.txt
easyshop.information.egg-info/not-zip-safe
easyshop.information.egg-info/requires.txt
easyshop.information.egg-info/top_level.txt
easyshop/information/__init__.py
easyshop/information/configure.zcml
easyshop/information/profiles.zcml
easyshop/information/tests.py
easyshop/information/adapters/__init__.py
easyshop/information/adapters/configure.zcml
easyshop/information/adapters/information_management.py
easyshop/information/browser/__init__.py
easyshop/information/browser/configure.zcml
easyshop/information/browser/information_container_view.pt
easyshop/information/browser/information_container_view.py
easyshop/information/browser/information_container_view_2.pt
easyshop/information/browser/information_container_view_2.py
easyshop/information/browser/information_page.pt
easyshop/information/browser/information_page.py
easyshop/information/browser/information_page_popup.pt
easyshop/information/browser/information_page_popup.py
easyshop/information/content/__init__.py
easyshop/information/content/containers.py
easyshop/information/content/information_page.py
easyshop/information/portlets/__init__.py
easyshop/information/portlets/configure.zcml
easyshop/information/portlets/information.pt
easyshop/information/portlets/information.py
easyshop/information/profiles/__init__.py
easyshop/information/profiles/default/factorytool.xml
easyshop/information/profiles/default/portlets.xml
easyshop/information/profiles/default/types.xml
easyshop/information/profiles/default/workflows.xml
easyshop/information/profiles/default/types/InformationContainer.xml
easyshop/information/profiles/default/types/InformationPage.xml